pyannote.algorithms-0.8-py3.6-nspkg.pth
pyannote/algorithms/__init__.py
pyannote/algorithms/_version.py
pyannote/algorithms/alignment/__init__.py
pyannote/algorithms/alignment/dtw.py
pyannote/algorithms/alignment/transcription.py
pyannote/algorithms/classification/__init__.py
pyannote/algorithms/classification/base.py
pyannote/algorithms/classification/gmm.py
pyannote/algorithms/classification/test_gmm.py
pyannote/algorithms/clustering/__init__.py
pyannote/algorithms/clustering/bic.py
pyannote/algorithms/clustering/chinese_whispers.py
pyannote/algorithms/clustering/hac/__init__.py
pyannote/algorithms/clustering/hac/constraint.py
pyannote/algorithms/clustering/hac/hac.py
pyannote/algorithms/clustering/hac/history.py
pyannote/algorithms/clustering/hac/linkage.py
pyannote/algorithms/clustering/hac/model.py
pyannote/algorithms/clustering/hac/stop.py
pyannote/algorithms/segmentation/__init__.py
pyannote/algorithms/segmentation/bic.py
pyannote/algorithms/segmentation/hmm.py
pyannote/algorithms/segmentation/sliding_window.py
pyannote/algorithms/stats/__init__.py
pyannote/algorithms/stats/gaussian.py
pyannote/algorithms/stats/lbg.py
pyannote/algorithms/stats/llr.py
pyannote/algorithms/tagging/__init__.py
pyannote/algorithms/tagging/base.py
pyannote/algorithms/tagging/label.py
pyannote/algorithms/tagging/mapping.py
pyannote/algorithms/tagging/segment.py
pyannote/algorithms/utils/Xy.py
pyannote/algorithms/utils/__init__.py
pyannote/algorithms/utils/sklearn.py
pyannote/algorithms/utils/test_viterbi.py
pyannote/algorithms/utils/viterbi.py
pyannote.algorithms-0.8.data/scripts/pyannote_hmm.py
pyannote.algorithms-0.8.dist-info/DESCRIPTION.rst
pyannote.algorithms-0.8.dist-info/METADATA
pyannote.algorithms-0.8.dist-info/RECORD
pyannote.algorithms-0.8.dist-info/WHEEL
pyannote.algorithms-0.8.dist-info/metadata.json
pyannote.algorithms-0.8.dist-info/namespace_packages.txt
pyannote.algorithms-0.8.dist-info/pbr.json
pyannote.algorithms-0.8.dist-info/top_level.txt
