Metadata-Version: 2.0
Name: pyannote.algorithms
Version: 0.8
Summary: PyAnnote algorithms
Home-page: http://herve.niderb.fr/
Author: Hervé Bredin
Author-email: bredin@limsi.fr
License: UNKNOWN
Platform: UNKNOWN
Classifier: Development Status :: 4 - Beta
Classifier: Intended Audience :: Science/Research
Classifier: License :: OSI Approved :: MIT License
Classifier: Natural Language :: English
Classifier: Programming Language :: Python :: 2
Classifier: Programming Language :: Python :: 2.7
Classifier: Programming Language :: Python :: 3
Classifier: Programming Language :: Python :: 3.4
Classifier: Programming Language :: Python :: 3.5
Classifier: Topic :: Scientific/Engineering
Requires-Dist: pyannote.core (>=1.3.1)
Requires-Dist: pyannote.parser (>=0.6.5)
Requires-Dist: scikit-learn (>=0.17)
Requires-Dist: scipy (>=0.17.0)
Requires-Dist: networkx (>=2.1)
Requires-Dist: munkres (>=1.0.7)
Requires-Dist: docopt (>=0.6.2)
Requires-Dist: joblib (>=0.9.4)
Requires-Dist: xarray (>=0.8.2)
Requires-Dist: sortedcollections (>=1.0.1)
Requires-Dist: six (>=1.10.0)
